diffused/__init__.py
diffused/__main__.py
diffused/cli.py
diffused/generate.py
diffused-1.0.1.dist-info/licenses/LICENSE
diffused-1.0.1.dist-info/METADATA
diffused-1.0.1.dist-info/WHEEL
diffused-1.0.1.dist-info/entry_points.txt
diffused-1.0.1.dist-info/top_level.txt
diffused-1.0.1.dist-info/RECORD
