Metadata-Version: 2.4
Name: diffused
Version: 1.0.1
Summary: Generate images with diffusion models.
Author-email: Mark <mark@remarkablemark.org>
Maintainer-email: Mark <mark@remarkablemark.org>
License-Expression: MIT
Project-URL: Homepage, https://github.com/ai-action/diffused
Project-URL: Documentation, https://ai-action.github.io/diffused/
Project-URL: Repository, https://github.com/ai-action/diffused
Project-URL: Issues, https://github.com/ai-action/diffused/issues
Project-URL: Changelog, https://github.com/ai-action/diffused/blob/master/CHANGELOG.md
Keywords: ai,artificial intelligence,cli,diffusers,diffusion,image-to-image,inpainting,machine learning,pytorch,stable diffusion,text-to-image
Classifier: Development Status :: 5 - Production/Stable
Classifier: Intended Audience :: Developers
Classifier: Intended Audience :: Education
Classifier: Intended Audience :: Science/Research
Classifier: Operating System :: OS Independent
Classifier: Programming Language :: Python :: 3
Classifier: Topic :: Scientific/Engineering :: Artificial Intelligence
Requires-Python: >=3.9
License-File: LICENSE
Requires-Dist: accelerate>=1.5.0
Requires-Dist: diffusers>=0.32.0
Requires-Dist: torch>=2.6.0
Requires-Dist: transformers>=4.50.0
Provides-Extra: build
Requires-Dist: build==1.3.0; extra == "build"
Requires-Dist: pyinstaller==6.16.0; extra == "build"
Requires-Dist: twine==6.2.0; extra == "build"
Provides-Extra: docs
Requires-Dist: pdoc==15.0.4; extra == "docs"
Provides-Extra: lint
Requires-Dist: black==25.11.0; extra == "lint"
Requires-Dist: isort==6.1.0; extra == "lint"
Requires-Dist: pre-commit==4.3.0; extra == "lint"
Requires-Dist: ruff==0.14.5; extra == "lint"
Provides-Extra: test
Requires-Dist: coverage==7.10.7; extra == "test"
Requires-Dist: pytest==8.4.2; extra == "test"
Dynamic: license-file
